celium/__init__.py
celium/async_client.py
celium/client.py
celium/config.py
celium/exceptions.py
celium/pagination.py
celium/version.py
celium/auth/__init__.py
celium/auth/api_key.py
celium/auth/base.py
celium/models/__init__.py
celium/models/docker_credentials.py
celium/models/executor.py
celium/models/pod.py
celium/models/ssh_key.py
celium/models/template.py
celium/resources/__init__.py
celium/resources/base.py
celium/resources/docker_credentials/__init__.py
celium/resources/docker_credentials/async_docker_credentials.py
celium/resources/docker_credentials/docker_credentials.py
celium/resources/docker_credentials/docker_credentials_core.py
celium/resources/pods/__init__.py
celium/resources/pods/async_pods.py
celium/resources/pods/pods.py
celium/resources/pods/pods_core.py
celium/resources/ssh_keys/__init__.py
celium/resources/ssh_keys/async_ssh_keys.py
celium/resources/ssh_keys/base.py
celium/resources/ssh_keys/ssh_keys.py
celium/resources/templates/__init__.py
celium/resources/templates/async_templates.py
celium/resources/templates/templates.py
celium/resources/templates/templates_core.py
celium/transport/__init__.py
celium/transport/base.py
celium/transport/httpx_async.py
celium/transport/httpx_sync.py
celium/utils/__init__.py
celium/utils/docker.py
celium/utils/logging.py
celium/utils/machine.py
celium/utils/retry.py
celium_sdk-0.1.3.dist-info/METADATA
celium_sdk-0.1.3.dist-info/WHEEL
celium_sdk-0.1.3.dist-info/top_level.txt
celium_sdk-0.1.3.dist-info/RECORD
